flask_augment
