Metadata-Version: 1.0
Name: Flask-Augment
Version: 0.5
Summary: Python decorators implementing contracts for flask framework
Home-page: https://github.com/thoughtnirvana/flask-augment
Author: Rahul Kumar
Author-email: rahul@thoughtnirvana.com
License: BSD
Platform: UNKNOWN
